{
  "players" : [ {
    "name" : "Luis",
    "scoreCard" : {
      "categories" : {
        "two" : null,
        "kniffel" : 0,
        "lowerSectionScore" : 0,
        "five" : null,
        "fourofakind" : null,
        "upperSectionScore" : 0,
        "four" : null,
        "bonus" : 0,
        "three" : null,
        "smallstraight" : null,
        "threeofakind" : null,
        "fullhouse" : null,
        "six" : null,
        "totalScore" : 0,
        "chance" : null,
        "largestraight" : null,
        "one" : null
      }
    }
  } ]
}